CHANGES.txt
CONTRIBUTORS.txt
MANIFEST.in
README.rst
TODO.txt
setup.py
docs/LICENSE.GPL
docs/LICENSE.txt
src/eastofeaton/__init__.py
src/eastofeaton.logopanel.egg-info/PKG-INFO
src/eastofeaton.logopanel.egg-info/SOURCES.txt
src/eastofeaton.logopanel.egg-info/dependency_links.txt
src/eastofeaton.logopanel.egg-info/entry_points.txt
src/eastofeaton.logopanel.egg-info/namespace_packages.txt
src/eastofeaton.logopanel.egg-info/not-zip-safe
src/eastofeaton.logopanel.egg-info/requires.txt
src/eastofeaton.logopanel.egg-info/top_level.txt
src/eastofeaton/logopanel/__init__.py
src/eastofeaton/logopanel/configure.zcml
src/eastofeaton/logopanel/testing.py
src/eastofeaton/logopanel/browser/__init__.py
src/eastofeaton/logopanel/browser/logopanel.pt
src/eastofeaton/logopanel/browser/logopanel.py
src/eastofeaton/logopanel/profiles/default/controlpanel.xml
src/eastofeaton/logopanel/profiles/default/metadata.xml
src/eastofeaton/logopanel/tests/__init__.py
src/eastofeaton/logopanel/tests/test_setup.py