Metadata-Version: 1.0
Name: eastofeaton.logopanel
Version: 1.1
Summary: A Plone control panel  to allow overriding the plone site logo
Home-page: https://github.com/cewing/eastofeaton.logopanel
Author: eleddy
Author-email: eleddy@eastofeaton.com
License: gpl
Keywords: plone
Platform: UNKNOWN
Classifier: Programming Language :: Python
